[{"txt":"Валовий зовнішній борг","apikod":"grossextdebt","periods":"q","dimensions":"s181, tzep","entrydate":"20010101"},{"txt":"Грошові агрегати","apikod":"monetary","periods":"m","dimensions":"k076, tzep","entrydate":"20030101"},{"txt":"Платіжний баланс","apikod":"balanceofpayments","periods":"m, q, y","dimensions":"t023, s181, tzep","entrydate":"20091231"},{"txt":"Показник фінансової звітності","apikod":"banksfinrep","periods":"m, q","dimensions":" r034, tzep, gr_bank","entrydate":"20120401"},{"txt":"Короткостроковий капітал","apikod":"shotextdebt","periods":"q","dimensions":"s181, tzep","entrydate":"20110101"},{"txt":"Міжнародна інвестиційна позиція ","apikod":"interinvestpos","periods":"q","dimensions":"s181, tzep","entrydate":"20020101"},{"txt":"Ліквідність","apikod":"liquidity","periods":"d","dimensions":" tzep","entrydate":"20110811"},{"txt":"Кредити, надані депозитними корпораціями ","apikod":"loan","periods":"m","dimensions":"odkodter, odr030, ods183ld, odk111, odk051, k040, tzep","entrydate":"20100201"},{"txt":"Депозити, залучені депозитними корпораціями","apikod":"deposit","periods":"m","dimensions":"odkodter, odr030, ods183dd, odk111, odk051, tzep","entrydate":"20100201"},{"txt":"Цінні папери, акції та інші форми участі в капіталі ","apikod":"securities","periods":"m","dimensions":"odr030, ods183sd, odk070, tzep","entrydate":"20100201"},{"txt":"Процентні ставки депозитних корпорацій","apikod":"mir","periods":"m","dimensions":"odkodter, ods180, odk111, odr030, tzep","entrydate":"20100201"},{"txt":"Доходи та витрати банків","apikod":"banksincexp","periods":"m, q","dimensions":" tzep","entrydate":"20090201"},{"txt":"Основні показники діяльності банків України","apikod":"basindbank","periods":"m, q","dimensions":" tzep","entrydate":"20160101"},{"txt":"Ціни","apikod":"inflation","periods":"m, y","dimensions":"mcrd081, ku, mcrk110, tzep","entrydate":"20070201"},{"txt":"Економічна активність ","apikod":"economicactivity","periods":"m, q, y","dimensions":"mcr210i, mcrk110, tzep","entrydate":"20100101"},{"txt":"Ринок праці","apikod":"labormarket","periods":"m, q, y","dimensions":"mcr210i, mcrk110, tzep","entrydate":"20030201"},{"txt":"Державні фінанси","apikod":"budget","periods":"m, y","dimensions":"mcr200p, tzep","entrydate":"20110201"},{"txt":"Кредити фізичних осіб","apikod":"klk","periods":"m","dimensions":"s080, r034, tzep","entrydate":"20170901"},{"txt":"Обороти і залишки на рахунку","apikod":"osb","periods":"m","dimensions":"r020, r034, t025, tzep","entrydate":"20170901"},{"txt":"Показники валютного ринку України","apikod":"kursf","periods":"d, m","dimensions":"r030, tzep","entrydate":"20120101"},{"txt":"Дані про міжнародні резерви","apikod":"res","periods":"m","dimensions":"tzep","entrydate":"20030101"},{"txt":"Огляд Національного банку України","apikod":"re","periods":"m","dimensions":"tzep","entrydate":"20030101"},{"txt":"Огляд депозитних корпорацій (крім Національного банку України)","apikod":"depcor","periods":"m","dimensions":"tzep","entrydate":"20030101"},{"txt":"Огляд депозитних корпорацій (включаючи Національний банк України)","apikod":"depcornbu","periods":"m","dimensions":"tzep","entrydate":"20030101"},{"txt":"Огляд інших фінансових корпорацій","apikod":"ofcs","periods":"q","dimensions":"tzep","entrydate":"20090101"},{"txt":"Огляд фінансових корпорацій","apikod":"fcs","periods":"q","dimensions":"tzep","entrydate":"20090101"},{"txt":"Балансовий звіт за секторами економіки. Україна. Центральний банк","apikod":"sr1","periods":"m","dimensions":"tzep","entrydate":"20030101"},{"txt":"Балансовий звіт за секторами економіки. Україна. Інші фінансові корпорації","apikod":"sr4","periods":"q","dimensions":"tzep","entrydate":"20090101"},{"txt":"Балансовий звіт за секторами економіки. Україна. Інші депозитні корпорації","apikod":"sr2","periods":"m","dimensions":"tzep","entrydate":"20030101"},{"txt":"Процентні ставки НБУ (облікова ставка та ставки за операціями постійного доступу)","apikod":"key","periods":"d","dimensions":"tzep","entrydate":"19920625"},{"txt":"Нормативи та складові розрахунку регулятивного капіталу банків ","apikod":"sklrk","periods":"m","dimensions":"tzep","entrydate":"20180301"},{"txt":"Економічні нормативи та ліміти відкритої валютної позиції","apikod":"ekn","periods":"d","dimensions":"tzep","entrydate":"20170228"},{"txt":"Окремі дані про міжнародні резерви","apikod":"res1","periods":"d, m, q, y","dimensions":"tzep","entrydate":"20030101"},{"txt":"Міжнародні золотовалютні резерви України (на основі щоденних даних з урахуванням уточненого курсу СПЗ)","apikod":"irad","periods":"m","dimensions":"tzep","entrydate":"20190101"},{"txt":"Міжнародні золотовалютні резерви України (на основі щомісячних даних)","apikod":"iram","periods":"m","dimensions":"tzep","entrydate":"20021201"},{"txt":"Окремі показники фінансової та наглядової звітності","apikod":"fsi","periods":"m","dimensions":"tzep","entrydate":"20180101"},{"txt":"Окремі показники фінансової та наглядової звітності","apikod":"fisin","periods":"m","dimensions":"ekpok","entrydate":"20180501"},{"txt":"Опитувальник","apikod":"survey","periods":"m","dimensions":"tzep","entrydate":"20190701"},{"txt":"Показники обсягу ввезеної / вивезеної банками готівкової іноземної валюти","apikod":"cashflow","periods":"m, y","dimensions":"r037","entrydate":"20120201"},{"txt":"Опитувальник (квартал)","apikod":"q_survey","periods":"q","dimensions":"kod_esrv,tzep","entrydate":"20140101"},{"txt":"Прямі інвестиції. Принцип спрямованості. Запаси","apikod":"fdis","periods":"q","dimensions":" ","entrydate":"20150101"},{"txt":"Прямі інвестиції. Принцип спрямованості. Потоки","apikod":"fdif","periods":"q","dimensions":" ","entrydate":"20150101"},{"txt":"Готівка в обігу","apikod":"emd","periods":"m","dimensions":"z060,z061,z053, tzep","entrydate":"19960901"}]